mp_utils/__init__.py
mp_utils/mp_utils.py
mp_facial_tool-0.0.2.dist-info/LICENSE
mp_facial_tool-0.0.2.dist-info/METADATA
mp_facial_tool-0.0.2.dist-info/WHEEL
mp_facial_tool-0.0.2.dist-info/top_level.txt
mp_facial_tool-0.0.2.dist-info/RECORD
