Metadata-Version: 2.1
Name: mp-facial-tool
Version: 0.0.2
Summary: some facial functions based mediapipe
Home-page: https://github.com/VERMANs/mp_utils
Author: VERMAN
Author-email: justverman@gmail.com
Classifier: Programming Language :: Python :: 3
Classifier: License :: OSI Approved :: MIT License
Classifier: Operating System :: OS Independent
License-File: LICENSE
